{"_path":"/test","_dir":"","_draft":false,"_partial":false,"_locale":"","title":"Test page","description":"","body":{"type":"root","children":[{"type":"element","tag":"h1","props":{"id":"test-page"},"children":[{"type":"text","value":"Test page"}]},{"type":"element","tag":"card","props":{"color":"red","icon":"i-material-symbols-arrow-cool-down","title":"Nice title"},"children":[{"type":"element","tag":"prose-ul","props":{},"children":[{"type":"element","tag":"prose-li","props":{},"children":[{"type":"element","tag":"p","props":{},"children":[{"type":"text","value":"Nice"}]}]},{"type":"element","tag":"prose-li","props":{},"children":[{"type":"element","tag":"p","props":{},"children":[{"type":"text","value":"list item"}]}]}]}]}],"toc":{"title":"","searchDepth":2,"depth":2,"links":[]}},"_type":"markdown","_id":"content:Test.md","_source":"content","_file":"Test.md","_stem":"Test","_extension":"md"}